hydev/__init__.py
hydev/common_pyproject.toml
hydev/hydlog.py
hydev/main.py
hydev/utils.py
hydev-5.1.0.dist-info/METADATA
hydev-5.1.0.dist-info/WHEEL
hydev-5.1.0.dist-info/entry_points.txt
hydev-5.1.0.dist-info/licenses/LICENSE
hydev-5.1.0.dist-info/RECORD
